tbk_api/__init__.py
tbk_api/dt.py
tbk_api-0.2.1.dist-info/WHEEL
tbk_api-0.2.1.dist-info/METADATA
tbk_api-0.2.1.dist-info/RECORD
