Metadata-Version: 2.1
Name: tbk-api
Version: 0.2.1
Summary: 淘宝客接口
Author: dev
Author-email: dev@qiyutech.tech
Requires-Python: >=3.9,<4.0
Classifier: Programming Language :: Python :: 3
Classifier: Programming Language :: Python :: 3.9
Requires-Dist: pydantic (>=1.7,<2)
